python1c/__init__.py
python1c/apiodata.py
python1c/core.py
python_to_1c-0.0.5.dist-info/LICENSE
python_to_1c-0.0.5.dist-info/METADATA
python_to_1c-0.0.5.dist-info/WHEEL
python_to_1c-0.0.5.dist-info/top_level.txt
python_to_1c-0.0.5.dist-info/RECORD
