Metadata-Version: 2.1
Name: python-to-1c
Version: 0.0.5
Summary: API for odata 1C
Home-page: https://github.com/kmvit/odatapython
Author: Andrey Galkin
Author-email: justscoundrel@yandex.ru
Classifier: Programming Language :: Python :: 3
Classifier: License :: OSI Approved :: MIT License
Classifier: Operating System :: OS Independent
License-File: LICENSE
Requires-Dist: requests
